{"error_code":"000","item":[{"item_name":"배추","item_code":"211","kind_name":"월동(1kg)","kind_code":"06","rank":"상품","rank_code":"04","unit":"10kg","day1":"당일 (03/18)","dpr1":"360","day2":"1일전 (03/17)","dpr2":"360","day3":"1주일전 (03/11)","dpr3":"360","day4":"2주일전 (03/04)","dpr4":"362","day5":"1개월전","dpr5":"406","day6":"1년전","dpr6":"1,256","day7":"일평년","dpr7":"1,080"},{"item_name":"배추","item_code":"211","kind_name":"월동(1kg)","kind_code":"06","rank":"중품","rank_code":"05","unit":"10kg","day1":"당일 (03/18)","dpr1":"260","day2":"1일전 (03/17)","dpr2":"260","day3":"1주일전 (03/11)","dpr3":"260","day4":"2주일전 (03/04)","dpr4":"262","day5":"1개월전","dpr5":"306","day6":"1년전","dpr6":"1,156","day7":"일평년","dpr7":"929"},{"item_name":"양배추","item_code":"212","kind_name":"양배추(1kg)","kind_code":"00","rank":"상품","rank_code":"04","unit":"8kg","day1":"당일 (03/18)","dpr1":"500","day2":"1일전 (03/17)","dpr2":"500","day3":"1주일전 (03/11)","dpr3":"500","day4":"2주일전 (03/04)","dpr4":"505","day5":"1개월전","dpr5":"513","day6":"1년전","dpr6":"975","day7":"일평년","dpr7":"835"},{"item_name":"양배추","item_code":"212","kind_name":"양배추(1kg)","kind_code":"00","rank":"중품","rank_code":"05","unit":"8kg","day1":"당일 (03/18)","dpr1":"375","day2":"1일전 (03/17)","dpr2":"375","day3":"1주일전 (03/11)","dpr3":"375","day4":"2주일전 (03/04)","dpr4":"380","day5":"1개월전","dpr5":"388","day6":"1년전","dpr6":"770","day7":"일평년","dpr7":"652"},{"item_name":"시금치","item_code":"213","kind_name":"시금치(1kg)","kind_code":"00","rank":"상품","rank_code":"04","unit":"4kg","day1":"당일 (03/18)","dpr1":"1,800","day2":"1일전 (03/17)","dpr2":"1,800","day3":"1주일전 (03/11)","dpr3":"1,550","day4":"2주일전 (03/04)","dpr4":"1,650","day5":"1개월전","dpr5":"1,650","day6":"1년전","dpr6":"1,490","day7":"일평년","dpr7":"1,768"},{"item_name":"시금치","item_code":"213","kind_name":"시금치(1kg)","kind_code":"00","rank":"중품","rank_code":"05","unit":"4kg","day1":"당일 (03/18)","dpr1":"1,350","day2":"1일전 (03/17)","dpr2":"1,350","day3":"1주일전 (03/11)","dpr3":"1,100","day4":"2주일전 (03/04)","dpr4":"1,200","day5":"1개월전","dpr5":"1,200","day6":"1년전","dpr6":"1,120","day7":"일평년","dpr7":"1,329"},{"item_name":"상추","item_code":"214","kind_name":"적(1kg)","kind_code":"01","rank":"상품","rank_code":"04","unit":"4kg","day1":"당일 (03/18)","dpr1":"2,800","day2":"1일전 (03/17)","dpr2":"2,800","day3":"1주일전 (03/11)","dpr3":"2,750","day4":"2주일전 (03/04)","dpr4":"2,700","day5":"1개월전","dpr5":"2,600","day6":"1년전","dpr6":"2,150","day7":"일평년","dpr7":"2,693"},{"item_name":"상추","item_code":"214","kind_name":"적(1kg)","kind_code":"01","rank":"중품","rank_code":"05","unit":"4kg","day1":"당일 (03/18)","dpr1":"2,200","day2":"1일전 (03/17)","dpr2":"2,175","day3":"1주일전 (03/11)","dpr3":"2,150","day4":"2주일전 (03/04)","dpr4":"2,100","day5":"1개월전","dpr5":"2,000","day6":"1년전","dpr6":"1,520","day7":"일평년","dpr7":"2,083"},{"item_name":"상추","item_code":"214","kind_name":"청(1kg)","kind_code":"02","rank":"상품","rank_code":"04","unit":"4kg","day1":"당일 (03/18)","dpr1":"2,500","day2":"1일전 (03/17)","dpr2":"2,400","day3":"1주일전 (03/11)","dpr3":"2,400","day4":"2주일전 (03/04)","dpr4":"2,450","day5":"1개월전","dpr5":"2,330","day6":"1년전","dpr6":"1,860","day7":"일평년","dpr7":"2,632"},{"item_name":"상추","item_code":"214","kind_name":"청(1kg)","kind_code":"02","rank":"중품","rank_code":"05","unit":"4kg","day1":"당일 (03/18)","dpr1":"2,000","day2":"1일전 (03/17)","dpr2":"1,900","day3":"1주일전 (03/11)","dpr3":"1,850","day4":"2주일전 (03/04)","dpr4":"1,900","day5":"1개월전","dpr5":"1,770","day6":"1년전","dpr6":"1,280","day7":"일평년","dpr7":"2,075"},{"item_name":"얼갈이배추","item_code":"215","kind_name":"얼갈이배추(1kg)","kind_code":"00","rank":"상품","rank_code":"04","unit":"4kg","day1":"당일 (03/18)","dpr1":"850","day2":"1일전 (03/17)","dpr2":"830","day3":"1주일전 (03/11)","dpr3":"830","day4":"2주일전 (03/04)","dpr4":"930","day5":"1개월전","dpr5":"918","day6":"1년전","dpr6":"1,242","day7":"일평년","dpr7":"1,300"},{"item_name":"얼갈이배추","item_code":"215","kind_name":"얼갈이배추(1kg)","kind_code":"00","rank":"중품","rank_code":"05","unit":"4kg","day1":"당일 (03/18)","dpr1":"600","day2":"1일전 (03/17)","dpr2":"600","day3":"1주일전 (03/11)","dpr3":"600","day4":"2주일전 (03/04)","dpr4":"720","day5":"1개월전","dpr5":"708","day6":"1년전","dpr6":"1,013","day7":"일평년","dpr7":"1,019"},{"item_name":"수박","item_code":"221","kind_name":"수박(1개)","kind_code":"00","rank":"상품","rank_code":"04","unit":"1개","day1":"당일 (03/18)","dpr1":"15,200","day2":"1일전 (03/17)","dpr2":"14,800","day3":"1주일전 (03/11)","dpr3":"14,200","day4":"2주일전 (03/04)","dpr4":"15,400","day5":"1개월전","dpr5":"18,000","day6":"1년전","dpr6":"14,800","day7":"일평년","dpr7":"16,920"},{"item_name":"수박","item_code":"221","kind_name":"수박(1개)","kind_code":"00","rank":"중품","rank_code":"05","unit":"1개","day1":"당일 (03/18)","dpr1":"12,200","day2":"1일전 (03/17)","dpr2":"11,800","day3":"1주일전 (03/11)","dpr3":"11,000","day4":"2주일전 (03/04)","dpr4":"12,200","day5":"1개월전","dpr5":"14,800","day6":"1년전","dpr6":"12,120","day7":"일평년","dpr7":"14,206"},{"item_name":"참외","item_code":"222","kind_name":"참외(1kg)","kind_code":"00","rank":"상품","rank_code":"04","unit":"10kg","day1":"당일 (03/18)","dpr1":"7,000","day2":"1일전 (03/17)","dpr2":"6,820","day3":"1주일전 (03/11)","dpr3":"5,140","day4":"2주일전 (03/04)","dpr4":"4,900","day5":"1개월전","dpr5":"-","day6":"1년전","dpr6":"-","day7":"일평년","dpr7":"-"},{"item_name":"참외","item_code":"222","kind_name":"참외(1kg)","kind_code":"00","rank":"중품","rank_code":"05","unit":"10kg","day1":"당일 (03/18)","dpr1":"6,160","day2":"1일전 (03/17)","dpr2":"5,980","day3":"1주일전 (03/11)","dpr3":"4,540","day4":"2주일전 (03/04)","dpr4":"4,400","day5":"1개월전","dpr5":"-","day6":"1년전","dpr6":"-","day7":"일평년","dpr7":"-"},{"item_name":"오이","item_code":"223","kind_name":"가시계통(1kg)","kind_code":"01","rank":"상품","rank_code":"04","unit":"10kg","day1":"당일 (03/18)","dpr1":"2,967","day2":"1일전 (03/17)","dpr2":"2,967","day3":"1주일전 (03/11)","dpr3":"2,867","day4":"2주일전 (03/04)","dpr4":"2,967","day5":"1개월전","dpr5":"3,327","day6":"1년전","dpr6":"2,587","day7":"일평년","dpr7":"2,623"},{"item_name":"오이","item_code":"223","kind_name":"가시계통(1kg)","kind_code":"01","rank":"중품","rank_code":"05","unit":"10kg","day1":"당일 (03/18)","dpr1":"2,600","day2":"1일전 (03/17)","dpr2":"2,600","day3":"1주일전 (03/11)","dpr3":"2,500","day4":"2주일전 (03/04)","dpr4":"2,600","day5":"1개월전","dpr5":"2,960","day6":"1년전","dpr6":"2,253","day7":"일평년","dpr7":"2,308"},{"item_name":"오이","item_code":"223","kind_name":"다다기계통(100개)","kind_code":"02","rank":"상품","rank_code":"04","unit":"100개","day1":"당일 (03/18)","dpr1":"72,445","day2":"1일전 (03/17)","dpr2":"73,778","day3":"1주일전 (03/11)","dpr3":"74,223","day4":"2주일전 (03/04)","dpr4":"78,222","day5":"1개월전","dpr5":"97,067","day6":"1년전","dpr6":"67,377","day7":"일평년","dpr7":"69,355"},{"item_name":"오이","item_code":"223","kind_name":"다다기계통(100개)","kind_code":"02","rank":"중품","rank_code":"05","unit":"100개","day1":"당일 (03/18)","dpr1":"63,111","day2":"1일전 (03/17)","dpr2":"64,444","day3":"1주일전 (03/11)","dpr3":"65,333","day4":"2주일전 (03/04)","dpr4":"69,333","day5":"1개월전","dpr5":"88,000","day6":"1년전","dpr6":"56,978","day7":"일평년","dpr7":"60,789"},{"item_name":"오이","item_code":"223","kind_name":"취청(50개)","kind_code":"03","rank":"상품","rank_code":"04","unit":"50개","day1":"당일 (03/18)","dpr1":"31,333","day2":"1일전 (03/17)","dpr2":"30,667","day3":"1주일전 (03/11)","dpr3":"30,667","day4":"2주일전 (03/04)","dpr4":"34,333","day5":"1개월전","dpr5":"36,400","day6":"1년전","dpr6":"29,767","day7":"일평년","dpr7":"30,681"},{"item_name":"오이","item_code":"223","kind_name":"취청(50개)","kind_code":"03","rank":"중품","rank_code":"05","unit":"50개","day1":"당일 (03/18)","dpr1":"26,000","day2":"1일전 (03/17)","dpr2":"26,000","day3":"1주일전 (03/11)","dpr3":"26,000","day4":"2주일전 (03/04)","dpr4":"29,333","day5":"1개월전","dpr5":"31,400","day6":"1년전","dpr6":"25,133","day7":"일평년","dpr7":"26,692"},{"item_name":"호박","item_code":"224","kind_name":"애호박(20개)","kind_code":"01","rank":"상품","rank_code":"04","unit":"20개","day1":"당일 (03/18)","dpr1":"29,200","day2":"1일전 (03/17)","dpr2":"29,000","day3":"1주일전 (03/11)","dpr3":"28,800","day4":"2주일전 (03/04)","dpr4":"30,400","day5":"1개월전","dpr5":"29,240","day6":"1년전","dpr6":"21,880","day7":"일평년","dpr7":"24,557"},{"item_name":"호박","item_code":"224","kind_name":"애호박(20개)","kind_code":"01","rank":"중품","rank_code":"05","unit":"20개","day1":"당일 (03/18)","dpr1":"25,400","day2":"1일전 (03/17)","dpr2":"25,200","day3":"1주일전 (03/11)","dpr3":"25,000","day4":"2주일전 (03/04)","dpr4":"26,400","day5":"1개월전","dpr5":"25,440","day6":"1년전","dpr6":"18,280","day7":"일평년","dpr7":"20,630"},{"item_name":"호박","item_code":"224","kind_name":"쥬키니(1kg)","kind_code":"02","rank":"상품","rank_code":"04","unit":"10kg","day1":"당일 (03/18)","dpr1":"2,900","day2":"1일전 (03/17)","dpr2":"2,820","day3":"1주일전 (03/11)","dpr3":"2,880","day4":"2주일전 (03/04)","dpr4":"2,640","day5":"1개월전","dpr5":"2,080","day6":"1년전","dpr6":"1,424","day7":"일평년","dpr7":"1,613"},{"item_name":"호박","item_code":"224","kind_name":"쥬키니(1kg)","kind_code":"02","rank":"중품","rank_code":"05","unit":"10kg","day1":"당일 (03/18)","dpr1":"2,520","day2":"1일전 (03/17)","dpr2":"2,440","day3":"1주일전 (03/11)","dpr3":"2,500","day4":"2주일전 (03/04)","dpr4":"2,260","day5":"1개월전","dpr5":"1,760","day6":"1년전","dpr6":"1,112","day7":"일평년","dpr7":"1,290"},{"item_name":"토마토","item_code":"225","kind_name":"토마토(1kg)","kind_code":"00","rank":"상품","rank_code":"04","unit":"5kg","day1":"당일 (03/18)","dpr1":"3,460","day2":"1일전 (03/17)","dpr2":"3,460","day3":"1주일전 (03/11)","dpr3":"3,700","day4":"2주일전 (03/04)","dpr4":"3,840","day5":"1개월전","dpr5":"3,740","day6":"1년전","dpr6":"3,168","day7":"일평년","dpr7":"3,283"},{"item_name":"토마토","item_code":"225","kind_name":"토마토(1kg)","kind_code":"00","rank":"중품","rank_code":"05","unit":"5kg","day1":"당일 (03/18)","dpr1":"3,040","day2":"1일전 (03/17)","dpr2":"3,040","day3":"1주일전 (03/11)","dpr3":"3,140","day4":"2주일전 (03/04)","dpr4":"3,260","day5":"1개월전","dpr5":"3,160","day6":"1년전","dpr6":"2,692","day7":"일평년","dpr7":"2,838"},{"item_name":"딸기","item_code":"226","kind_name":"딸기(1kg)","kind_code":"00","rank":"상품","rank_code":"04","unit":"2kg","day1":"당일 (03/18)","dpr1":"9,400","day2":"1일전 (03/17)","dpr2":"9,400","day3":"1주일전 (03/11)","dpr3":"9,600","day4":"2주일전 (03/04)","dpr4":"9,800","day5":"1개월전","dpr5":"10,560","day6":"1년전","dpr6":"8,080","day7":"일평년","dpr7":"8,302"},{"item_name":"딸기","item_code":"226","kind_name":"딸기(1kg)","kind_code":"00","rank":"중품","rank_code":"05","unit":"2kg","day1":"당일 (03/18)","dpr1":"7,000","day2":"1일전 (03/17)","dpr2":"7,000","day3":"1주일전 (03/11)","dpr3":"7,200","day4":"2주일전 (03/04)","dpr4":"7,400","day5":"1개월전","dpr5":"8,160","day6":"1년전","dpr6":"6,240","day7":"일평년","dpr7":"6,312"},{"item_name":"무","item_code":"231","kind_name":"월동(1kg)","kind_code":"06","rank":"상품","rank_code":"04","unit":"20kg","day1":"당일 (03/18)","dpr1":"430","day2":"1일전 (03/17)","dpr2":"430","day3":"1주일전 (03/11)","dpr3":"444","day4":"2주일전 (03/04)","dpr4":"388","day5":"1개월전","dpr5":"411","day6":"1년전","dpr6":"514","day7":"일평년","dpr7":"497"},{"item_name":"무","item_code":"231","kind_name":"월동(1kg)","kind_code":"06","rank":"중품","rank_code":"05","unit":"20kg","day1":"당일 (03/18)","dpr1":"340","day2":"1일전 (03/17)","dpr2":"340","day3":"1주일전 (03/11)","dpr3":"354","day4":"2주일전 (03/04)","dpr4":"298","day5":"1개월전","dpr5":"311","day6":"1년전","dpr6":"424","day7":"일평년","dpr7":"403"},{"item_name":"당근","item_code":"232","kind_name":"무세척(1kg)","kind_code":"01","rank":"상품","rank_code":"04","unit":"20kg","day1":"당일 (03/18)","dpr1":"980","day2":"1일전 (03/17)","dpr2":"930","day3":"1주일전 (03/11)","dpr3":"850","day4":"2주일전 (03/04)","dpr4":"850","day5":"1개월전","dpr5":"942","day6":"1년전","dpr6":"4,636","day7":"일평년","dpr7":"1,235"},{"item_name":"당근","item_code":"232","kind_name":"무세척(1kg)","kind_code":"01","rank":"중품","rank_code":"05","unit":"20kg","day1":"당일 (03/18)","dpr1":"780","day2":"1일전 (03/17)","dpr2":"740","day3":"1주일전 (03/11)","dpr3":"660","day4":"2주일전 (03/04)","dpr4":"660","day5":"1개월전","dpr5":"752","day6":"1년전","dpr6":"4,106","day7":"일평년","dpr7":"996"},{"item_name":"당근","item_code":"232","kind_name":"세척(수입)(1kg)","kind_code":"10","rank":"중품","rank_code":"05","unit":"10kg","day1":"당일 (03/18)","dpr1":"990","day2":"1일전 (03/17)","dpr2":"990","day3":"1주일전 (03/11)","dpr3":"990","day4":"2주일전 (03/04)","dpr4":"990","day5":"1개월전","dpr5":"1,002","day6":"1년전","dpr6":"1,032","day7":"일평년","dpr7":"958"},{"item_name":"열무","item_code":"233","kind_name":"열무(1kg)","kind_code":"00","rank":"상품","rank_code":"04","unit":"4kg","day1":"당일 (03/18)","dpr1":"1,190","day2":"1일전 (03/17)","dpr2":"1,140","day3":"1주일전 (03/11)","dpr3":"1,060","day4":"2주일전 (03/04)","dpr4":"1,080","day5":"1개월전","dpr5":"940","day6":"1년전","dpr6":"1,246","day7":"일평년","dpr7":"1,471"},{"item_name":"열무","item_code":"233","kind_name":"열무(1kg)","kind_code":"00","rank":"중품","rank_code":"05","unit":"4kg","day1":"당일 (03/18)","dpr1":"940","day2":"1일전 (03/17)","dpr2":"890","day3":"1주일전 (03/11)","dpr3":"850","day4":"2주일전 (03/04)","dpr4":"830","day5":"1개월전","dpr5":"730","day6":"1년전","dpr6":"968","day7":"일평년","dpr7":"1,157"},{"item_name":"건고추","item_code":"241","kind_name":"화건(1kg)","kind_code":"00","rank":"상품","rank_code":"04","unit":"30kg","day1":"당일 (03/18)","dpr1":"10,833","day2":"1일전 (03/17)","dpr2":"10,833","day3":"1주일전 (03/11)","dpr3":"11,000","day4":"2주일전 (03/04)","dpr4":"11,000","day5":"1개월전","dpr5":"11,000","day6":"1년전","dpr6":"15,167","day7":"일평년","dpr7":"13,133"},{"item_name":"건고추","item_code":"241","kind_name":"화건(1kg)","kind_code":"00","rank":"중품","rank_code":"05","unit":"30kg","day1":"당일 (03/18)","dpr1":"9,333","day2":"1일전 (03/17)","dpr2":"9,333","day3":"1주일전 (03/11)","dpr3":"9,500","day4":"2주일전 (03/04)","dpr4":"9,500","day5":"1개월전","dpr5":"9,500","day6":"1년전","dpr6":"13,500","day7":"일평년","dpr7":"11,989"},{"item_name":"건고추","item_code":"241","kind_name":"양건(1kg)","kind_code":"02","rank":"상품","rank_code":"04","unit":"30kg","day1":"당일 (03/18)","dpr1":"13,833","day2":"1일전 (03/17)","dpr2":"14,167","day3":"1주일전 (03/11)","dpr3":"14,167","day4":"2주일전 (03/04)","dpr4":"14,167","day5":"1개월전","dpr5":"14,167","day6":"1년전","dpr6":"19,833","day7":"일평년","dpr7":"16,478"},{"item_name":"건고추","item_code":"241","kind_name":"양건(1kg)","kind_code":"02","rank":"중품","rank_code":"05","unit":"30kg","day1":"당일 (03/18)","dpr1":"12,333","day2":"1일전 (03/17)","dpr2":"12,667","day3":"1주일전 (03/11)","dpr3":"12,667","day4":"2주일전 (03/04)","dpr4":"12,667","day5":"1개월전","dpr5":"12,667","day6":"1년전","dpr6":"18,167","day7":"일평년","dpr7":"15,311"},{"item_name":"풋고추","item_code":"242","kind_name":"풋고추(1kg)","kind_code":"00","rank":"상품","rank_code":"04","unit":"10kg","day1":"당일 (03/18)","dpr1":"8,380","day2":"1일전 (03/17)","dpr2":"8,700","day3":"1주일전 (03/11)","dpr3":"9,300","day4":"2주일전 (03/04)","dpr4":"9,200","day5":"1개월전","dpr5":"8,748","day6":"1년전","dpr6":"5,604","day7":"일평년","dpr7":"7,727"},{"item_name":"풋고추","item_code":"242","kind_name":"풋고추(1kg)","kind_code":"00","rank":"중품","rank_code":"05","unit":"10kg","day1":"당일 (03/18)","dpr1":"7,180","day2":"1일전 (03/17)","dpr2":"7,500","day3":"1주일전 (03/11)","dpr3":"8,100","day4":"2주일전 (03/04)","dpr4":"8,000","day5":"1개월전","dpr5":"7,540","day6":"1년전","dpr6":"4,696","day7":"일평년","dpr7":"7,002"},{"item_name":"풋고추","item_code":"242","kind_name":"꽈리고추(1kg)","kind_code":"02","rank":"상품","rank_code":"04","unit":"4kg","day1":"당일 (03/18)","dpr1":"6,250","day2":"1일전 (03/17)","dpr2":"6,250","day3":"1주일전 (03/11)","dpr3":"7,100","day4":"2주일전 (03/04)","dpr4":"7,450","day5":"1개월전","dpr5":"6,670","day6":"1년전","dpr6":"6,600","day7":"일평년","dpr7":"6,930"},{"item_name":"풋고추","item_code":"242","kind_name":"꽈리고추(1kg)","kind_code":"02","rank":"중품","rank_code":"05","unit":"4kg","day1":"당일 (03/18)","dpr1":"5,100","day2":"1일전 (03/17)","dpr2":"5,100","day3":"1주일전 (03/11)","dpr3":"5,950","day4":"2주일전 (03/04)","dpr4":"6,250","day5":"1개월전","dpr5":"5,520","day6":"1년전","dpr6":"5,460","day7":"일평년","dpr7":"6,026"},{"item_name":"풋고추","item_code":"242","kind_name":"청양고추(1kg)","kind_code":"03","rank":"상품","rank_code":"04","unit":"10kg","day1":"당일 (03/18)","dpr1":"6,080","day2":"1일전 (03/17)","dpr2":"6,340","day3":"1주일전 (03/11)","dpr3":"6,820","day4":"2주일전 (03/04)","dpr4":"7,660","day5":"1개월전","dpr5":"5,336","day6":"1년전","dpr6":"5,940","day7":"일평년","dpr7":"9,253"},{"item_name":"풋고추","item_code":"242","kind_name":"청양고추(1kg)","kind_code":"03","rank":"중품","rank_code":"05","unit":"10kg","day1":"당일 (03/18)","dpr1":"5,380","day2":"1일전 (03/17)","dpr2":"5,540","day3":"1주일전 (03/11)","dpr3":"6,020","day4":"2주일전 (03/04)","dpr4":"6,860","day5":"1개월전","dpr5":"4,792","day6":"1년전","dpr6":"5,172","day7":"일평년","dpr7":"8,366"},{"item_name":"붉은고추","item_code":"243","kind_name":"붉은고추(1kg)","kind_code":"00","rank":"상품","rank_code":"04","unit":"10kg","day1":"당일 (03/18)","dpr1":"9,800","day2":"1일전 (03/17)","dpr2":"9,700","day3":"1주일전 (03/11)","dpr3":"8,000","day4":"2주일전 (03/04)","dpr4":"6,100","day5":"1개월전","dpr5":"5,476","day6":"1년전","dpr6":"12,648","day7":"일평년","dpr7":"10,027"},{"item_name":"붉은고추","item_code":"243","kind_name":"붉은고추(1kg)","kind_code":"00","rank":"중품","rank_code":"05","unit":"10kg","day1":"당일 (03/18)","dpr1":"8,780","day2":"1일전 (03/17)","dpr2":"8,680","day3":"1주일전 (03/11)","dpr3":"6,980","day4":"2주일전 (03/04)","dpr4":"5,080","day5":"1개월전","dpr5":"4,556","day6":"1년전","dpr6":"11,312","day7":"일평년","dpr7":"9,129"},{"item_name":"피마늘","item_code":"244","kind_name":"한지(1kg)","kind_code":"03","rank":"상품","rank_code":"04","unit":"10kg","day1":"당일 (03/18)","dpr1":"5,067","day2":"1일전 (03/17)","dpr2":"5,067","day3":"1주일전 (03/11)","dpr3":"5,067","day4":"2주일전 (03/04)","dpr4":"5,067","day5":"1개월전","dpr5":"5,067","day6":"1년전","dpr6":"5,213","day7":"일평년","dpr7":"6,956"},{"item_name":"피마늘","item_code":"244","kind_name":"한지(1kg)","kind_code":"03","rank":"중품","rank_code":"05","unit":"10kg","day1":"당일 (03/18)","dpr1":"4,500","day2":"1일전 (03/17)","dpr2":"4,500","day3":"1주일전 (03/11)","dpr3":"4,500","day4":"2주일전 (03/04)","dpr4":"4,500","day5":"1개월전","dpr5":"4,500","day6":"1년전","dpr6":"4,500","day7":"일평년","dpr7":"5,967"},{"item_name":"피마늘","item_code":"244","kind_name":"난지(1kg)","kind_code":"04","rank":"상품","rank_code":"04","unit":"10kg","day1":"당일 (03/18)","dpr1":"2,740","day2":"1일전 (03/17)","dpr2":"2,740","day3":"1주일전 (03/11)","dpr3":"2,740","day4":"2주일전 (03/04)","dpr4":"2,780","day5":"1개월전","dpr5":"2,780","day6":"1년전","dpr6":"3,944","day7":"일평년","dpr7":"3,560"},{"item_name":"피마늘","item_code":"244","kind_name":"난지(1kg)","kind_code":"04","rank":"중품","rank_code":"05","unit":"10kg","day1":"당일 (03/18)","dpr1":"2,260","day2":"1일전 (03/17)","dpr2":"2,260","day3":"1주일전 (03/11)","dpr3":"2,260","day4":"2주일전 (03/04)","dpr4":"2,300","day5":"1개월전","dpr5":"2,360","day6":"1년전","dpr6":"3,402","day7":"일평년","dpr7":"3,159"},{"item_name":"양파","item_code":"245","kind_name":"양파(1kg)","kind_code":"00","rank":"상품","rank_code":"04","unit":"15kg","day1":"당일 (03/18)","dpr1":"722","day2":"1일전 (03/17)","dpr2":"722","day3":"1주일전 (03/11)","dpr3":"720","day4":"2주일전 (03/04)","dpr4":"720","day5":"1개월전","dpr5":"776","day6":"1년전","dpr6":"1,924","day7":"일평년","dpr7":"1,101"},{"item_name":"양파","item_code":"245","kind_name":"양파(1kg)","kind_code":"00","rank":"중품","rank_code":"05","unit":"15kg","day1":"당일 (03/18)","dpr1":"612","day2":"1일전 (03/17)","dpr2":"612","day3":"1주일전 (03/11)","dpr3":"610","day4":"2주일전 (03/04)","dpr4":"610","day5":"1개월전","dpr5":"676","day6":"1년전","dpr6":"1,804","day7":"일평년","dpr7":"976"},{"item_name":"파","item_code":"246","kind_name":"대파(1kg)","kind_code":"00","rank":"상품","rank_code":"04","unit":"1kg","day1":"당일 (03/18)","dpr1":"1,250","day2":"1일전 (03/17)","dpr2":"1,250","day3":"1주일전 (03/11)","dpr3":"1,250","day4":"2주일전 (03/04)","dpr4":"1,270","day5":"1개월전","dpr5":"1,308","day6":"1년전","dpr6":"2,228","day7":"일평년","dpr7":"1,842"},{"item_name":"파","item_code":"246","kind_name":"대파(1kg)","kind_code":"00","rank":"중품","rank_code":"05","unit":"1kg","day1":"당일 (03/18)","dpr1":"1,020","day2":"1일전 (03/17)","dpr2":"1,020","day3":"1주일전 (03/11)","dpr3":"1,020","day4":"2주일전 (03/04)","dpr4":"1,040","day5":"1개월전","dpr5":"1,068","day6":"1년전","dpr6":"1,980","day7":"일평년","dpr7":"1,555"},{"item_name":"파","item_code":"246","kind_name":"쪽파(1kg)","kind_code":"02","rank":"상품","rank_code":"04","unit":"1kg","day1":"당일 (03/18)","dpr1":"1,720","day2":"1일전 (03/17)","dpr2":"1,760","day3":"1주일전 (03/11)","dpr3":"1,620","day4":"2주일전 (03/04)","dpr4":"1,960","day5":"1개월전","dpr5":"2,012","day6":"1년전","dpr6":"2,256","day7":"일평년","dpr7":"2,569"},{"item_name":"파","item_code":"246","kind_name":"쪽파(1kg)","kind_code":"02","rank":"중품","rank_code":"05","unit":"1kg","day1":"당일 (03/18)","dpr1":"1,420","day2":"1일전 (03/17)","dpr2":"1,460","day3":"1주일전 (03/11)","dpr3":"1,340","day4":"2주일전 (03/04)","dpr4":"1,680","day5":"1개월전","dpr5":"1,732","day6":"1년전","dpr6":"1,848","day7":"일평년","dpr7":"2,154"},{"item_name":"생강","item_code":"247","kind_name":"국산(1kg)","kind_code":"00","rank":"상품","rank_code":"04","unit":"10kg","day1":"당일 (03/18)","dpr1":"4,880","day2":"1일전 (03/17)","dpr2":"4,750","day3":"1주일전 (03/11)","dpr3":"4,060","day4":"2주일전 (03/04)","dpr4":"3,630","day5":"1개월전","dpr5":"3,330","day6":"1년전","dpr6":"5,850","day7":"일평년","dpr7":"4,370"},{"item_name":"생강","item_code":"247","kind_name":"국산(1kg)","kind_code":"00","rank":"중품","rank_code":"05","unit":"10kg","day1":"당일 (03/18)","dpr1":"4,360","day2":"1일전 (03/17)","dpr2":"4,230","day3":"1주일전 (03/11)","dpr3":"3,560","day4":"2주일전 (03/04)","dpr4":"3,180","day5":"1개월전","dpr5":"2,880","day6":"1년전","dpr6":"5,350","day7":"일평년","dpr7":"3,890"},{"item_name":"생강","item_code":"247","kind_name":"수입(1kg)","kind_code":"01","rank":"중품","rank_code":"05","unit":"10kg","day1":"당일 (03/18)","dpr1":"8,160","day2":"1일전 (03/17)","dpr2":"8,160","day3":"1주일전 (03/11)","dpr3":"7,500","day4":"2주일전 (03/04)","dpr4":"6,980","day5":"1개월전","dpr5":"6,980","day6":"1년전","dpr6":"3,620","day7":"일평년","dpr7":"4,007"},{"item_name":"미나리","item_code":"252","kind_name":"미나리(1kg)","kind_code":"00","rank":"상품","rank_code":"04","unit":"7.5kg","day1":"당일 (03/18)","dpr1":"3,570","day2":"1일전 (03/17)","dpr2":"3,550","day3":"1주일전 (03/11)","dpr3":"3,590","day4":"2주일전 (03/04)","dpr4":"3,610","day5":"1개월전","dpr5":"3,006","day6":"1년전","dpr6":"3,134","day7":"일평년","dpr7":"3,395"},{"item_name":"미나리","item_code":"252","kind_name":"미나리(1kg)","kind_code":"00","rank":"중품","rank_code":"05","unit":"7.5kg","day1":"당일 (03/18)","dpr1":"3,090","day2":"1일전 (03/17)","dpr2":"3,070","day3":"1주일전 (03/11)","dpr3":"3,110","day4":"2주일전 (03/04)","dpr4":"3,100","day5":"1개월전","dpr5":"2,526","day6":"1년전","dpr6":"2,706","day7":"일평년","dpr7":"2,916"},{"item_name":"깻잎","item_code":"253","kind_name":"깻잎(1kg)","kind_code":"00","rank":"상품","rank_code":"04","unit":"2kg","day1":"당일 (03/18)","dpr1":"9,500","day2":"1일전 (03/17)","dpr2":"9,000","day3":"1주일전 (03/11)","dpr3":"9,200","day4":"2주일전 (03/04)","dpr4":"8,400","day5":"1개월전","dpr5":"8,340","day6":"1년전","dpr6":"7,460","day7":"일평년","dpr7":"8,752"},{"item_name":"깻잎","item_code":"253","kind_name":"깻잎(1kg)","kind_code":"00","rank":"중품","rank_code":"05","unit":"2kg","day1":"당일 (03/18)","dpr1":"8,000","day2":"1일전 (03/17)","dpr2":"7,500","day3":"1주일전 (03/11)","dpr3":"7,700","day4":"2주일전 (03/04)","dpr4":"7,000","day5":"1개월전","dpr5":"6,800","day6":"1년전","dpr6":"5,920","day7":"일평년","dpr7":"7,165"},{"item_name":"피망","item_code":"255","kind_name":"청(1kg)","kind_code":"00","rank":"상품","rank_code":"04","unit":"10kg","day1":"당일 (03/18)","dpr1":"4,960","day2":"1일전 (03/17)","dpr2":"4,960","day3":"1주일전 (03/11)","dpr3":"5,260","day4":"2주일전 (03/04)","dpr4":"5,880","day5":"1개월전","dpr5":"7,052","day6":"1년전","dpr6":"5,076","day7":"일평년","dpr7":"6,164"},{"item_name":"피망","item_code":"255","kind_name":"청(1kg)","kind_code":"00","rank":"중품","rank_code":"05","unit":"10kg","day1":"당일 (03/18)","dpr1":"4,340","day2":"1일전 (03/17)","dpr2":"4,360","day3":"1주일전 (03/11)","dpr3":"4,620","day4":"2주일전 (03/04)","dpr4":"5,120","day5":"1개월전","dpr5":"6,248","day6":"1년전","dpr6":"4,292","day7":"일평년","dpr7":"5,557"},{"item_name":"파프리카","item_code":"256","kind_name":"파프리카(1kg)","kind_code":"00","rank":"상품","rank_code":"04","unit":"5kg","day1":"당일 (03/18)","dpr1":"5,560","day2":"1일전 (03/17)","dpr2":"5,520","day3":"1주일전 (03/11)","dpr3":"5,320","day4":"2주일전 (03/04)","dpr4":"5,600","day5":"1개월전","dpr5":"6,000","day6":"1년전","dpr6":"7,168","day7":"일평년","dpr7":"6,834"},{"item_name":"파프리카","item_code":"256","kind_name":"파프리카(1kg)","kind_code":"00","rank":"중품","rank_code":"05","unit":"5kg","day1":"당일 (03/18)","dpr1":"4,640","day2":"1일전 (03/17)","dpr2":"4,600","day3":"1주일전 (03/11)","dpr3":"4,400","day4":"2주일전 (03/04)","dpr4":"4,680","day5":"1개월전","dpr5":"5,080","day6":"1년전","dpr6":"6,016","day7":"일평년","dpr7":"5,830"},{"item_name":"멜론","item_code":"257","kind_name":"멜론(1kg)","kind_code":"00","rank":"상품","rank_code":"04","unit":"8kg","day1":"당일 (03/18)","dpr1":"3,750","day2":"1일전 (03/17)","dpr2":"3,750","day3":"1주일전 (03/11)","dpr3":"4,100","day4":"2주일전 (03/04)","dpr4":"4,800","day5":"1개월전","dpr5":"4,890","day6":"1년전","dpr6":"6,920","day7":"일평년","dpr7":"6,054"},{"item_name":"멜론","item_code":"257","kind_name":"멜론(1kg)","kind_code":"00","rank":"중품","rank_code":"05","unit":"8kg","day1":"당일 (03/18)","dpr1":"3,150","day2":"1일전 (03/17)","dpr2":"3,150","day3":"1주일전 (03/11)","dpr3":"3,475","day4":"2주일전 (03/04)","dpr4":"4,175","day5":"1개월전","dpr5":"4,190","day6":"1년전","dpr6":"6,064","day7":"일평년","dpr7":"5,173"},{"item_name":"깐마늘(국산)","item_code":"258","kind_name":"깐마늘(국산)(1kg)","kind_code":"01","rank":"상품","rank_code":"04","unit":"20kg","day1":"당일 (03/18)","dpr1":"3,570","day2":"1일전 (03/17)","dpr2":"3,590","day3":"1주일전 (03/11)","dpr3":"3,700","day4":"2주일전 (03/04)","dpr4":"3,700","day5":"1개월전","dpr5":"3,760","day6":"1년전","dpr6":"6,276","day7":"일평년","dpr7":"5,527"},{"item_name":"깐마늘(국산)","item_code":"258","kind_name":"깐마늘(국산)(1kg)","kind_code":"01","rank":"중품","rank_code":"05","unit":"20kg","day1":"당일 (03/18)","dpr1":"2,870","day2":"1일전 (03/17)","dpr2":"2,890","day3":"1주일전 (03/11)","dpr3":"3,000","day4":"2주일전 (03/04)","dpr4":"3,000","day5":"1개월전","dpr5":"3,040","day6":"1년전","dpr6":"5,222","day7":"일평년","dpr7":"4,759"},{"item_name":"방울토마토","item_code":"422","kind_name":"방울토마토(1kg)","kind_code":"01","rank":"상품","rank_code":"04","unit":"5kg","day1":"당일 (03/18)","dpr1":"6,440","day2":"1일전 (03/17)","dpr2":"6,120","day3":"1주일전 (03/11)","dpr3":"5,600","day4":"2주일전 (03/04)","dpr4":"5,200","day5":"1개월전","dpr5":"4,944","day6":"1년전","dpr6":"5,000","day7":"일평년","dpr7":"4,571"},{"item_name":"방울토마토","item_code":"422","kind_name":"방울토마토(1kg)","kind_code":"01","rank":"중품","rank_code":"05","unit":"5kg","day1":"당일 (03/18)","dpr1":"5,680","day2":"1일전 (03/17)","dpr2":"5,400","day3":"1주일전 (03/11)","dpr3":"4,880","day4":"2주일전 (03/04)","dpr4":"4,520","day5":"1개월전","dpr5":"4,304","day6":"1년전","dpr6":"4,240","day7":"일평년","dpr7":"3,824"}]}